file_parsing/__init__.py
file_parsing/simple.py
file_parsing_sample-0.0.1.dist-info/LICENSE.txt
file_parsing_sample-0.0.1.dist-info/METADATA
file_parsing_sample-0.0.1.dist-info/WHEEL
file_parsing_sample-0.0.1.dist-info/top_level.txt
file_parsing_sample-0.0.1.dist-info/RECORD
