Metadata-Version: 2.1
Name: file-parsing-sample
Version: 0.0.1
Summary: A small package exercising file parsing
Home-page: https://github.com/pypa/sampleproject
Author: Sue Hannum
Author-email: sue.hannum@sas.com
License: UNKNOWN
Project-URL: Bug Tracker, https://github.com/pypa/sampleproject/issues
Platform: UNKNOWN
Classifier: Development Status :: 3 - Alpha
Classifier: Intended Audience :: Developers
Classifier: Programming Language :: Python :: 3
Classifier: License :: OSI Approved :: MIT License
Classifier: Operating System :: OS Independent
Requires-Python: >=3.6
